{"duplicatesPercentage":20.93023256,"nodes":{"children":[{"LOC":27,"path":"/src/t3/Dummya.java","prefix_id":"T3-7","label":"/src/t3/Dummya.java","id":7,"children":[{"prefix_id":"T3-5","attributes":{"LOC":9,"endLine":9,"startLine":1,"file":"Dummya.java","clone":"public class Dummya {\n    void sumProd(int n) {\n\t\tdouble sum=0.0; //C1\n\t\tdouble prod =1.0;\n\t\tfor (int i=1; i<=n; i++)\n\t\t\t{sum=sum + i;\n\t\t\tprod = prod * i;\n\t\t\tfoo(sum, prod); }}\n}\n"},"id":5}]},{"LOC":27,"path":"/src/t1/CopyOneB.java","prefix_id":"T3-9","label":"/src/t1/CopyOneB.java","id":9,"children":[{"prefix_id":"T3-3","attributes":{"LOC":9,"endLine":9,"startLine":1,"file":"CopyOneB.java","clone":"public class Copy {\r\n    void sumProd(int n) {\r\n\t\tdouble sum=0.0; //C1'\r\n\t\tdouble prod =1.0; //C \r\n\t\tfor (int i=1; i<=n; i++)\r\n\t\t\t{sum=sum + i; \r\n\t\t\tprod = prod * i;\r\n\t\t\tfoo(sum, prod); }}\r\n}\r\n"},"id":3}]},{"LOC":27,"path":"/src/orig/OriginalCopy.java","prefix_id":"T3-11","label":"/src/orig/OriginalCopy.java","id":11,"children":[{"prefix_id":"T3-4","attributes":{"LOC":9,"endLine":9,"startLine":1,"file":"OriginalCopy.java","clone":"public class Copy {\n    void sumProd(int n) {\n\t\tdouble sum=0.0; //C1\n\t\tdouble prod =1.0;\n\t\tfor (int i=1; i<=n; i++)\n\t\t\t{sum=sum + i;\n\t\t\tprod = prod * i;\n\t\t\tfoo(sum, prod); }}\n}\n"},"id":4}]}]},"label":"project://testDUP","relations":[{"target":4,"source":3},{"target":5,"source":3},{"target":5,"source":4}],"duplicatesLOC":27,"totalLOC":129,"cloneClasses":[{"LOC":27,"id":2,"children":[{"prefix_id":"T3-3","attributes":{"LOC":9,"path":"/src/t1/CopyOneB.java","percentageOfClass":33.33333333,"percentageOfProject":6.976744186,"endLine":9,"startLine":1,"file":"CopyOneB.java","clone":"public class Copy {\r\n    void sumProd(int n) {\r\n\t\tdouble sum=0.0; //C1'\r\n\t\tdouble prod =1.0; //C \r\n\t\tfor (int i=1; i<=n; i++)\r\n\t\t\t{sum=sum + i; \r\n\t\t\tprod = prod * i;\r\n\t\t\tfoo(sum, prod); }}\r\n}\r\n"},"id":3},{"prefix_id":"T3-4","attributes":{"LOC":9,"path":"/src/orig/OriginalCopy.java","percentageOfClass":33.33333333,"percentageOfProject":6.976744186,"endLine":9,"startLine":1,"file":"OriginalCopy.java","clone":"public class Copy {\n    void sumProd(int n) {\n\t\tdouble sum=0.0; //C1\n\t\tdouble prod =1.0;\n\t\tfor (int i=1; i<=n; i++)\n\t\t\t{sum=sum + i;\n\t\t\tprod = prod * i;\n\t\t\tfoo(sum, prod); }}\n}\n"},"id":4},{"prefix_id":"T3-5","attributes":{"LOC":9,"path":"/src/t3/Dummya.java","percentageOfClass":33.33333333,"percentageOfProject":6.976744186,"endLine":9,"startLine":1,"file":"Dummya.java","clone":"public class Dummya {\n    void sumProd(int n) {\n\t\tdouble sum=0.0; //C1\n\t\tdouble prod =1.0;\n\t\tfor (int i=1; i<=n; i++)\n\t\t\t{sum=sum + i;\n\t\t\tprod = prod * i;\n\t\t\tfoo(sum, prod); }}\n}\n"},"id":5}],"prefix_id":"T3-2","percentageOfProject":20.93023256}],"fullSources":[{"path":"/src/t3/Dummya.java","source":"public class Dummya {\n    void sumProd(int n) {\n\t\tdouble sum=0.0; //C1\n\t\tdouble prod =1.0;\n\t\tfor (int i=1; i<=n; i++)\n\t\t\t{sum=sum + i;\n\t\t\tprod = prod * i;\n\t\t\tfoo(sum, prod); }}\n}\n"},{"path":"/src/t1/CopyOneB.java","source":"public class Copy {\r\n    void sumProd(int n) {\r\n\t\tdouble sum=0.0; //C1'\r\n\t\tdouble prod =1.0; //C \r\n\t\tfor (int i=1; i<=n; i++)\r\n\t\t\t{sum=sum + i; \r\n\t\t\tprod = prod * i;\r\n\t\t\tfoo(sum, prod); }}\r\n}\r\n"},{"path":"/src/orig/OriginalCopy.java","source":"public class Copy {\n    void sumProd(int n) {\n\t\tdouble sum=0.0; //C1\n\t\tdouble prod =1.0;\n\t\tfor (int i=1; i<=n; i++)\n\t\t\t{sum=sum + i;\n\t\t\tprod = prod * i;\n\t\t\tfoo(sum, prod); }}\n}\n"}]}